{"id":"recording-items;todo-list-app-should-clear-text-input-field-when-an-item-is-added;linux-5-15-0-1038-azure;firefox-113-0","name":"Todo List App should clear text input field when an item is added","title":"Todo List App should clear text input field when an item is added","manual":false,"testSteps":[{"number":1,"description":"Alice starts with an empty todo list","startTime":1686655911696,"children":[{"number":2,"description":"Alice navigates to '/'","startTime":1686655911698,"children":[],"reportData":[],"screenshots":[],"duration":404,"result":"SUCCESS"},{"number":3,"description":"Alice ensures that website title does equal 'Serenity/JS TodoApp'","startTime":1686655912112,"children":[],"reportData":[],"screenshots":[],"duration":39,"result":"SUCCESS"}],"reportData":[],"screenshots":[],"duration":466,"result":"SUCCESS"},{"number":4,"description":"Alice records an item called 'buy some cheese'","startTime":1686655912172,"children":[{"number":5,"description":"Alice enters 'buy some cheese' into \"What needs to be done?\" input box","startTime":1686655912174,"children":[],"reportData":[],"screenshots":[],"duration":47,"result":"SUCCESS"},{"number":6,"description":"Alice presses key Enter in \"What needs to be done?\" input box","startTime":1686655912231,"children":[],"reportData":[],"screenshots":[],"duration":58,"result":"SUCCESS"},{"number":7,"description":"Alice waits until displayed items does contain 'buy some cheese'","startTime":1686655912301,"children":[],"reportData":[],"screenshots":[],"duration":25,"result":"SUCCESS"}],"reportData":[],"screenshots":[],"duration":165,"result":"SUCCESS"},{"number":8,"description":"Alice ensures that the value of \"What needs to be done?\" input box does equal ''","startTime":1686655912347,"children":[],"reportData":[],"screenshots":[],"duration":6,"result":"SUCCESS"},{"number":9,"description":"Alice ensures that <<persisted item called buy some cheese>>.name does equal 'buy some cheese'","startTime":1686655912364,"children":[],"reportData":[],"screenshots":[],"duration":6,"result":"SUCCESS"},{"number":10,"description":"Alice ensures that <<persisted item called buy some cheese>>.completed does equal false","startTime":1686655912381,"children":[],"reportData":[],"screenshots":[],"duration":4,"result":"SUCCESS"}],"userStory":{"id":"recording-items","storyName":"Recording items","path":"","type":"feature"},"startTime":1686655911673,"featureTag":{"name":"Recording items","type":"feature","displayName":"Recording items"},"tags":[{"name":"Recording items","type":"feature","displayName":"Recording items"},{"name":"retried","type":"tag","displayName":"retried"},{"name":"Linux 5.15.0-1038-azure","type":"platform","platformName":"Linux","platformVersion":"5.15.0-1038-azure","displayName":"Linux 5.15.0-1038-azure"},{"name":"firefox 113.0","type":"browser","browserName":"firefox","browserVersion":"113.0","displayName":"firefox 113.0"}],"testSource":"Playwright","context":"linux,firefox","driver":"firefox","result":"SUCCESS","duration":762}