{"id":"multi-actor-scenarios;todo-list-app-supports-multiple-actors-using-separate-browsers;linux-5-15-0-1041-azure;webkit-17-0","name":"Todo List App supports multiple actors using separate browsers","title":"Todo List App supports multiple actors using separate browsers","manual":false,"testSteps":[{"number":1,"description":"Alice starts with a list containing 1 items","startTime":1689998918164,"children":[{"number":2,"description":"Alice starts with an empty todo list","startTime":1689998918167,"children":[{"number":3,"description":"Alice navigates to '/'","startTime":1689998918169,"children":[],"reportData":[],"screenshots":[],"duration":1415,"result":"SUCCESS"},{"number":4,"description":"Alice ensures that website title does equal 'Serenity/JS TodoApp'","startTime":1689998919596,"children":[],"reportData":[],"screenshots":[],"duration":14,"result":"SUCCESS"}],"reportData":[],"screenshots":[],"duration":1454,"result":"SUCCESS"},{"number":5,"description":"Alice records an item called 'Feed the cat'","startTime":1689998919633,"children":[{"number":6,"description":"Alice enters 'Feed the cat' into \"What needs to be done?\" input box","startTime":1689998919634,"children":[],"reportData":[],"screenshots":[],"duration":66,"result":"SUCCESS"},{"number":7,"description":"Alice presses key Enter in \"What needs to be done?\" input box","startTime":1689998919713,"children":[],"reportData":[],"screenshots":[],"duration":65,"result":"SUCCESS"},{"number":8,"description":"Alice waits until displayed items does contain 'Feed the cat'","startTime":1689998919792,"children":[],"reportData":[],"screenshots":[],"duration":84,"result":"SUCCESS"}],"reportData":[],"screenshots":[],"duration":254,"result":"SUCCESS"}],"reportData":[],"screenshots":[],"duration":1733,"result":"SUCCESS"},{"number":9,"description":"Bob starts with a list containing 1 items","startTime":1689998919924,"children":[{"number":10,"description":"Bob starts with an empty todo list","startTime":1689998919925,"children":[{"number":11,"description":"Bob navigates to '/'","startTime":1689998919927,"children":[],"reportData":[],"screenshots":[],"duration":898,"result":"SUCCESS"},{"number":12,"description":"Bob ensures that website title does equal 'Serenity/JS TodoApp'","startTime":1689998920836,"children":[],"reportData":[],"screenshots":[],"duration":15,"result":"SUCCESS"}],"reportData":[],"screenshots":[],"duration":937,"result":"SUCCESS"},{"number":13,"description":"Bob records an item called 'Walk the dog'","startTime":1689998920874,"children":[{"number":14,"description":"Bob enters 'Walk the dog' into \"What needs to be done?\" input box","startTime":1689998920876,"children":[],"reportData":[],"screenshots":[],"duration":49,"result":"SUCCESS"},{"number":15,"description":"Bob presses key Enter in \"What needs to be done?\" input box","startTime":1689998920939,"children":[],"reportData":[],"screenshots":[],"duration":59,"result":"SUCCESS"},{"number":16,"description":"Bob waits until displayed items does contain 'Walk the dog'","startTime":1689998921009,"children":[],"reportData":[],"screenshots":[],"duration":71,"result":"SUCCESS"}],"reportData":[],"screenshots":[],"duration":217,"result":"SUCCESS"}],"reportData":[],"screenshots":[],"duration":1187,"result":"SUCCESS"},{"number":17,"description":"Alice ensures that displayed items does equal [ 'Feed the cat' ]","startTime":1689998921127,"children":[],"reportData":[],"screenshots":[],"duration":12,"result":"SUCCESS"},{"number":18,"description":"Bob ensures that displayed items does equal [ 'Walk the dog' ]","startTime":1689998921153,"children":[],"reportData":[],"screenshots":[],"duration":15,"result":"SUCCESS"}],"userStory":{"id":"multi-actor-scenarios","storyName":"Multi-actor scenarios","path":"","type":"feature"},"startTime":1689998916926,"featureTag":{"name":"Multi-actor scenarios","type":"feature","displayName":"Multi-actor scenarios"},"tags":[{"name":"Multi-actor scenarios","type":"feature","displayName":"Multi-actor scenarios"},{"name":"retried","type":"tag","displayName":"retried"},{"name":"Linux 5.15.0-1041-azure","type":"platform","platformName":"Linux","platformVersion":"5.15.0-1041-azure","displayName":"Linux 5.15.0-1041-azure"},{"name":"webkit 17.0","type":"browser","browserName":"webkit","browserVersion":"17.0","displayName":"webkit 17.0"}],"testSource":"Playwright","context":"linux,safari","driver":"webkit","result":"SUCCESS","duration":4325}