{"id":"multi-actor-scenarios;todo-list-app-supports-multiple-actors-using-separate-browsers;linux-5-15-0-1040-azure;firefox-113-0","name":"Todo List App supports multiple actors using separate browsers","title":"Todo List App supports multiple actors using separate browsers","manual":false,"testSteps":[{"number":1,"description":"Alice starts with a list containing 1 items","startTime":1687815125799,"children":[{"number":2,"description":"Alice starts with an empty todo list","startTime":1687815125800,"children":[{"number":3,"description":"Alice navigates to '/'","startTime":1687815125800,"children":[],"reportData":[],"screenshots":[],"duration":1305,"result":"SUCCESS"},{"number":4,"description":"Alice ensures that website title does equal 'Serenity/JS TodoApp'","startTime":1687815127116,"children":[],"reportData":[],"screenshots":[],"duration":88,"result":"SUCCESS"}],"reportData":[],"screenshots":[],"duration":1414,"result":"SUCCESS"},{"number":5,"description":"Alice records an item called 'Feed the cat'","startTime":1687815127225,"children":[{"number":6,"description":"Alice enters 'Feed the cat' into \"What needs to be done?\" input box","startTime":1687815127225,"children":[],"reportData":[],"screenshots":[],"duration":137,"result":"SUCCESS"},{"number":7,"description":"Alice presses key Enter in \"What needs to be done?\" input box","startTime":1687815127374,"children":[],"reportData":[],"screenshots":[],"duration":109,"result":"SUCCESS"},{"number":8,"description":"Alice waits until displayed items does contain 'Feed the cat'","startTime":1687815127494,"children":[],"reportData":[],"screenshots":[],"duration":41,"result":"SUCCESS"}],"reportData":[],"screenshots":[],"duration":320,"result":"SUCCESS"}],"reportData":[],"screenshots":[],"duration":1757,"result":"SUCCESS"},{"number":9,"description":"Bob starts with a list containing 1 items","startTime":1687815127585,"children":[{"number":10,"description":"Bob starts with an empty todo list","startTime":1687815127586,"children":[{"number":11,"description":"Bob navigates to '/'","startTime":1687815127586,"children":[],"reportData":[],"screenshots":[],"duration":464,"result":"SUCCESS"},{"number":12,"description":"Bob ensures that website title does equal 'Serenity/JS TodoApp'","startTime":1687815128060,"children":[],"reportData":[],"screenshots":[],"duration":37,"result":"SUCCESS"}],"reportData":[],"screenshots":[],"duration":521,"result":"SUCCESS"},{"number":13,"description":"Bob records an item called 'Walk the dog'","startTime":1687815128118,"children":[{"number":14,"description":"Bob enters 'Walk the dog' into \"What needs to be done?\" input box","startTime":1687815128119,"children":[],"reportData":[],"screenshots":[],"duration":69,"result":"SUCCESS"},{"number":15,"description":"Bob presses key Enter in \"What needs to be done?\" input box","startTime":1687815128199,"children":[],"reportData":[],"screenshots":[],"duration":69,"result":"SUCCESS"},{"number":16,"description":"Bob waits until displayed items does contain 'Walk the dog'","startTime":1687815128279,"children":[],"reportData":[],"screenshots":[],"duration":27,"result":"SUCCESS"}],"reportData":[],"screenshots":[],"duration":198,"result":"SUCCESS"}],"reportData":[],"screenshots":[],"duration":741,"result":"SUCCESS"},{"number":17,"description":"Alice ensures that displayed items does equal [ 'Feed the cat' ]","startTime":1687815128340,"children":[],"reportData":[],"screenshots":[],"duration":27,"result":"SUCCESS"},{"number":18,"description":"Bob ensures that displayed items does equal [ 'Walk the dog' ]","startTime":1687815128381,"children":[],"reportData":[],"screenshots":[],"duration":15,"result":"SUCCESS"}],"userStory":{"id":"multi-actor-scenarios","storyName":"Multi-actor scenarios","path":"","type":"feature"},"startTime":1687815125001,"featureTag":{"name":"Multi-actor scenarios","type":"feature","displayName":"Multi-actor scenarios"},"tags":[{"name":"Multi-actor scenarios","type":"feature","displayName":"Multi-actor scenarios"},{"name":"retried","type":"tag","displayName":"retried"},{"name":"Linux 5.15.0-1040-azure","type":"platform","platformName":"Linux","platformVersion":"5.15.0-1040-azure","displayName":"Linux 5.15.0-1040-azure"},{"name":"firefox 113.0","type":"browser","browserName":"firefox","browserVersion":"113.0","displayName":"firefox 113.0"}],"testSource":"Playwright","context":"linux,firefox","driver":"firefox","result":"SUCCESS","duration":3508}