{"id":"multi-actor-scenarios;todo-list-app-supports-multiple-actors-using-separate-browsers;linux-5-15-0-1041-azure;webkit-17-0","name":"Todo List App supports multiple actors using separate browsers","title":"Todo List App supports multiple actors using separate browsers","manual":false,"testSteps":[{"number":1,"description":"Alice starts with a list containing 1 items","startTime":1690866479775,"children":[{"number":2,"description":"Alice starts with an empty todo list","startTime":1690866479777,"children":[{"number":3,"description":"Alice navigates to '/'","startTime":1690866479778,"children":[],"reportData":[],"screenshots":[],"duration":1140,"result":"SUCCESS"},{"number":4,"description":"Alice ensures that website title does equal 'Serenity/JS TodoApp'","startTime":1690866480932,"children":[],"reportData":[],"screenshots":[],"duration":11,"result":"SUCCESS"}],"reportData":[],"screenshots":[],"duration":1177,"result":"SUCCESS"},{"number":5,"description":"Alice records an item called 'Feed the cat'","startTime":1690866480967,"children":[{"number":6,"description":"Alice enters 'Feed the cat' into \"What needs to be done?\" input box","startTime":1690866480968,"children":[],"reportData":[],"screenshots":[],"duration":45,"result":"SUCCESS"},{"number":7,"description":"Alice presses key Enter in \"What needs to be done?\" input box","startTime":1690866481025,"children":[],"reportData":[],"screenshots":[],"duration":47,"result":"SUCCESS"},{"number":8,"description":"Alice waits until displayed items does contain 'Feed the cat'","startTime":1690866481085,"children":[],"reportData":[],"screenshots":[],"duration":63,"result":"SUCCESS"}],"reportData":[],"screenshots":[],"duration":191,"result":"SUCCESS"}],"reportData":[],"screenshots":[],"duration":1394,"result":"SUCCESS"},{"number":9,"description":"Bob starts with a list containing 1 items","startTime":1690866481190,"children":[{"number":10,"description":"Bob starts with an empty todo list","startTime":1690866481190,"children":[{"number":11,"description":"Bob navigates to '/'","startTime":1690866481191,"children":[],"reportData":[],"screenshots":[],"duration":1058,"result":"SUCCESS"},{"number":12,"description":"Bob ensures that website title does equal 'Serenity/JS TodoApp'","startTime":1690866482260,"children":[],"reportData":[],"screenshots":[],"duration":5,"result":"SUCCESS"}],"reportData":[],"screenshots":[],"duration":1085,"result":"SUCCESS"},{"number":13,"description":"Bob records an item called 'Walk the dog'","startTime":1690866482286,"children":[{"number":14,"description":"Bob enters 'Walk the dog' into \"What needs to be done?\" input box","startTime":1690866482287,"children":[],"reportData":[],"screenshots":[],"duration":53,"result":"SUCCESS"},{"number":15,"description":"Bob presses key Enter in \"What needs to be done?\" input box","startTime":1690866482352,"children":[],"reportData":[],"screenshots":[],"duration":60,"result":"SUCCESS"},{"number":16,"description":"Bob waits until displayed items does contain 'Walk the dog'","startTime":1690866482423,"children":[],"reportData":[],"screenshots":[],"duration":58,"result":"SUCCESS"}],"reportData":[],"screenshots":[],"duration":205,"result":"SUCCESS"}],"reportData":[],"screenshots":[],"duration":1311,"result":"SUCCESS"},{"number":17,"description":"Alice ensures that displayed items does equal [ 'Feed the cat' ]","startTime":1690866482514,"children":[],"reportData":[],"screenshots":[],"duration":16,"result":"SUCCESS"},{"number":18,"description":"Bob ensures that displayed items does equal [ 'Walk the dog' ]","startTime":1690866482543,"children":[],"reportData":[],"screenshots":[],"duration":9,"result":"SUCCESS"}],"userStory":{"id":"multi-actor-scenarios","storyName":"Multi-actor scenarios","path":"","type":"feature"},"startTime":1690866478484,"featureTag":{"name":"Multi-actor scenarios","type":"feature","displayName":"Multi-actor scenarios"},"tags":[{"name":"Multi-actor scenarios","type":"feature","displayName":"Multi-actor scenarios"},{"name":"retried","type":"tag","displayName":"retried"},{"name":"Linux 5.15.0-1041-azure","type":"platform","platformName":"Linux","platformVersion":"5.15.0-1041-azure","displayName":"Linux 5.15.0-1041-azure"},{"name":"webkit 17.0","type":"browser","browserName":"webkit","browserVersion":"17.0","displayName":"webkit 17.0"}],"testSource":"Playwright","context":"linux,safari","driver":"webkit","result":"SUCCESS","duration":4135}