{"id":"multi-actor-scenarios;todo-list-app-supports-multiple-actors-using-separate-browsers;linux-5-15-0-1024-azure;firefox-107-0","name":"Todo List App supports multiple actors using separate browsers","title":"Todo List App supports multiple actors using separate browsers","manual":false,"testSteps":[{"number":1,"description":"Alice starts with a list containing 1 items","startTime":1671487352323,"children":[{"number":2,"description":"Alice starts with an empty todo list","startTime":1671487352334,"children":[{"number":3,"description":"Alice navigates to '/'","startTime":1671487352345,"children":[],"reportData":[],"screenshots":[],"duration":1197,"result":"SUCCESS"},{"number":4,"description":"Alice ensures that website title does equal 'Serenity/JS TodoApp'","startTime":1671487353552,"children":[],"reportData":[],"screenshots":[],"duration":71,"result":"SUCCESS"}],"reportData":[],"screenshots":[],"duration":1289,"result":"SUCCESS"},{"number":5,"description":"Alice records an item called 'Feed the cat'","startTime":1671487353634,"children":[{"number":6,"description":"Alice enters 'Feed the cat' into \"What needs to be done?\" input box","startTime":1671487353645,"children":[],"reportData":[],"screenshots":[],"duration":288,"result":"SUCCESS"},{"number":7,"description":"Alice presses key Enter in \"What needs to be done?\" input box","startTime":1671487353944,"children":[],"reportData":[],"screenshots":[],"duration":46,"result":"SUCCESS"},{"number":8,"description":"Alice waits up to 5s, polling every 500ms, until displayed items does contain 'Feed the cat'","startTime":1671487354000,"children":[],"reportData":[],"screenshots":[],"duration":54,"result":"SUCCESS"}],"reportData":[],"screenshots":[],"duration":421,"result":"SUCCESS"}],"reportData":[],"screenshots":[],"duration":1732,"result":"SUCCESS"},{"number":9,"description":"Bob starts with a list containing 1 items","startTime":1671487354091,"children":[{"number":10,"description":"Bob starts with an empty todo list","startTime":1671487354102,"children":[{"number":11,"description":"Bob navigates to '/'","startTime":1671487354112,"children":[],"reportData":[],"screenshots":[],"duration":406,"result":"SUCCESS"},{"number":12,"description":"Bob ensures that website title does equal 'Serenity/JS TodoApp'","startTime":1671487354529,"children":[],"reportData":[],"screenshots":[],"duration":43,"result":"SUCCESS"}],"reportData":[],"screenshots":[],"duration":470,"result":"SUCCESS"},{"number":13,"description":"Bob records an item called 'Walk the dog'","startTime":1671487354587,"children":[{"number":14,"description":"Bob enters 'Walk the dog' into \"What needs to be done?\" input box","startTime":1671487354597,"children":[],"reportData":[],"screenshots":[],"duration":148,"result":"SUCCESS"},{"number":15,"description":"Bob presses key Enter in \"What needs to be done?\" input box","startTime":1671487354756,"children":[],"reportData":[],"screenshots":[],"duration":36,"result":"SUCCESS"},{"number":16,"description":"Bob waits up to 5s, polling every 500ms, until displayed items does contain 'Walk the dog'","startTime":1671487354803,"children":[],"reportData":[],"screenshots":[],"duration":17,"result":"SUCCESS"}],"reportData":[],"screenshots":[],"duration":233,"result":"SUCCESS"}],"reportData":[],"screenshots":[],"duration":729,"result":"SUCCESS"},{"number":17,"description":"Alice ensures that displayed items does equal [ 'Feed the cat' ]","startTime":1671487354837,"children":[],"reportData":[],"screenshots":[],"duration":27,"result":"SUCCESS"},{"number":18,"description":"Bob ensures that displayed items does equal [ 'Walk the dog' ]","startTime":1671487354880,"children":[],"reportData":[],"screenshots":[],"duration":19,"result":"SUCCESS"}],"userStory":{"id":"multi-actor-scenarios","storyName":"Multi-actor scenarios","path":"","type":"feature"},"startTime":1671487351491,"featureTag":{"name":"Multi-actor scenarios","type":"feature","displayName":"Multi-actor scenarios"},"tags":[{"name":"Multi-actor scenarios","type":"feature","displayName":"Multi-actor scenarios"},{"name":"retried","type":"tag","displayName":"retried"},{"name":"Linux 5.15.0-1024-azure","type":"platform","platformName":"Linux","platformVersion":"5.15.0-1024-azure","displayName":"Linux 5.15.0-1024-azure"},{"name":"firefox 107.0","type":"browser","browserName":"firefox","browserVersion":"107.0","displayName":"firefox 107.0"}],"testSource":"Playwright","context":"linux,firefox","driver":"firefox","result":"SUCCESS","duration":3486}