{"id":"multi-actor-scenarios;todo-list-app-supports-multiple-actors-using-separate-browsers;linux-5-15-0-1037-azure;chromium-114-0-5735-35","name":"Todo List App supports multiple actors using separate browsers","title":"Todo List App supports multiple actors using separate browsers","manual":false,"testSteps":[{"number":1,"description":"Alice starts with a list containing 1 items","startTime":1685384717524,"children":[{"number":2,"description":"Alice starts with an empty todo list","startTime":1685384717541,"children":[{"number":3,"description":"Alice navigates to '/'","startTime":1685384717553,"children":[],"reportData":[],"screenshots":[],"duration":449,"result":"SUCCESS"},{"number":4,"description":"Alice ensures that website title does equal 'Serenity/JS TodoApp'","startTime":1685384718012,"children":[],"reportData":[],"screenshots":[],"duration":11,"result":"SUCCESS"}],"reportData":[],"screenshots":[],"duration":482,"result":"SUCCESS"},{"number":5,"description":"Alice records an item called 'Feed the cat'","startTime":1685384718034,"children":[{"number":6,"description":"Alice enters 'Feed the cat' into \"What needs to be done?\" input box","startTime":1685384718045,"children":[],"reportData":[],"screenshots":[],"duration":148,"result":"SUCCESS"},{"number":7,"description":"Alice presses key Enter in \"What needs to be done?\" input box","startTime":1685384718203,"children":[],"reportData":[],"screenshots":[],"duration":31,"result":"SUCCESS"},{"number":8,"description":"Alice waits until displayed items does contain 'Feed the cat'","startTime":1685384718245,"children":[],"reportData":[],"screenshots":[],"duration":104,"result":"SUCCESS"}],"reportData":[],"screenshots":[],"duration":315,"result":"SUCCESS"}],"reportData":[],"screenshots":[],"duration":826,"result":"SUCCESS"},{"number":9,"description":"Bob starts with a list containing 1 items","startTime":1685384718377,"children":[{"number":10,"description":"Bob starts with an empty todo list","startTime":1685384718388,"children":[{"number":11,"description":"Bob navigates to '/'","startTime":1685384718399,"children":[],"reportData":[],"screenshots":[],"duration":294,"result":"SUCCESS"},{"number":12,"description":"Bob ensures that website title does equal 'Serenity/JS TodoApp'","startTime":1685384718703,"children":[],"reportData":[],"screenshots":[],"duration":7,"result":"SUCCESS"}],"reportData":[],"screenshots":[],"duration":323,"result":"SUCCESS"},{"number":13,"description":"Bob records an item called 'Walk the dog'","startTime":1685384718722,"children":[{"number":14,"description":"Bob enters 'Walk the dog' into \"What needs to be done?\" input box","startTime":1685384718733,"children":[],"reportData":[],"screenshots":[],"duration":58,"result":"SUCCESS"},{"number":15,"description":"Bob presses key Enter in \"What needs to be done?\" input box","startTime":1685384718802,"children":[],"reportData":[],"screenshots":[],"duration":28,"result":"SUCCESS"},{"number":16,"description":"Bob waits until displayed items does contain 'Walk the dog'","startTime":1685384718841,"children":[],"reportData":[],"screenshots":[],"duration":51,"result":"SUCCESS"}],"reportData":[],"screenshots":[],"duration":170,"result":"SUCCESS"}],"reportData":[],"screenshots":[],"duration":516,"result":"SUCCESS"},{"number":17,"description":"Alice ensures that displayed items does equal [ 'Feed the cat' ]","startTime":1685384718908,"children":[],"reportData":[],"screenshots":[],"duration":14,"result":"SUCCESS"},{"number":18,"description":"Bob ensures that displayed items does equal [ 'Walk the dog' ]","startTime":1685384718937,"children":[],"reportData":[],"screenshots":[],"duration":25,"result":"SUCCESS"}],"userStory":{"id":"multi-actor-scenarios","storyName":"Multi-actor scenarios","path":"","type":"feature"},"startTime":1685384717071,"featureTag":{"name":"Multi-actor scenarios","type":"feature","displayName":"Multi-actor scenarios"},"tags":[{"name":"Multi-actor scenarios","type":"feature","displayName":"Multi-actor scenarios"},{"name":"retried","type":"tag","displayName":"retried"},{"name":"Linux 5.15.0-1037-azure","type":"platform","platformName":"Linux","platformVersion":"5.15.0-1037-azure","displayName":"Linux 5.15.0-1037-azure"},{"name":"chromium 114.0.5735.35","type":"browser","browserName":"chromium","browserVersion":"114.0.5735.35","displayName":"chromium 114.0.5735.35"}],"testSource":"Playwright","context":"linux,chrome","driver":"chromium","result":"SUCCESS","duration":1963}