{"id":"multi-actor-scenarios;todo-list-app-supports-multiple-actors-using-separate-browsers;linux-5-15-0-1037-azure;firefox-113-0","name":"Todo List App supports multiple actors using separate browsers","title":"Todo List App supports multiple actors using separate browsers","manual":false,"testSteps":[{"number":1,"description":"Alice starts with a list containing 1 items","startTime":1684893211536,"children":[{"number":2,"description":"Alice starts with an empty todo list","startTime":1684893211553,"children":[{"number":3,"description":"Alice navigates to '/'","startTime":1684893211563,"children":[],"reportData":[],"screenshots":[],"duration":1165,"result":"SUCCESS"},{"number":4,"description":"Alice ensures that website title does equal 'Serenity/JS TodoApp'","startTime":1684893212740,"children":[],"reportData":[],"screenshots":[],"duration":21,"result":"SUCCESS"}],"reportData":[],"screenshots":[],"duration":1208,"result":"SUCCESS"},{"number":5,"description":"Alice records an item called 'Feed the cat'","startTime":1684893212771,"children":[{"number":6,"description":"Alice enters 'Feed the cat' into \"What needs to be done?\" input box","startTime":1684893212782,"children":[],"reportData":[],"screenshots":[],"duration":150,"result":"SUCCESS"},{"number":7,"description":"Alice presses key Enter in \"What needs to be done?\" input box","startTime":1684893212942,"children":[],"reportData":[],"screenshots":[],"duration":38,"result":"SUCCESS"},{"number":8,"description":"Alice waits until displayed items does contain 'Feed the cat'","startTime":1684893212991,"children":[],"reportData":[],"screenshots":[],"duration":52,"result":"SUCCESS"}],"reportData":[],"screenshots":[],"duration":272,"result":"SUCCESS"}],"reportData":[],"screenshots":[],"duration":1507,"result":"SUCCESS"},{"number":9,"description":"Bob starts with a list containing 1 items","startTime":1684893213068,"children":[{"number":10,"description":"Bob starts with an empty todo list","startTime":1684893213079,"children":[{"number":11,"description":"Bob navigates to '/'","startTime":1684893213090,"children":[],"reportData":[],"screenshots":[],"duration":356,"result":"SUCCESS"},{"number":12,"description":"Bob ensures that website title does equal 'Serenity/JS TodoApp'","startTime":1684893213457,"children":[],"reportData":[],"screenshots":[],"duration":36,"result":"SUCCESS"}],"reportData":[],"screenshots":[],"duration":414,"result":"SUCCESS"},{"number":13,"description":"Bob records an item called 'Walk the dog'","startTime":1684893213504,"children":[{"number":14,"description":"Bob enters 'Walk the dog' into \"What needs to be done?\" input box","startTime":1684893213515,"children":[],"reportData":[],"screenshots":[],"duration":88,"result":"SUCCESS"},{"number":15,"description":"Bob presses key Enter in \"What needs to be done?\" input box","startTime":1684893213614,"children":[],"reportData":[],"screenshots":[],"duration":32,"result":"SUCCESS"},{"number":16,"description":"Bob waits until displayed items does contain 'Walk the dog'","startTime":1684893213657,"children":[],"reportData":[],"screenshots":[],"duration":25,"result":"SUCCESS"}],"reportData":[],"screenshots":[],"duration":179,"result":"SUCCESS"}],"reportData":[],"screenshots":[],"duration":615,"result":"SUCCESS"},{"number":17,"description":"Alice ensures that displayed items does equal [ 'Feed the cat' ]","startTime":1684893213697,"children":[],"reportData":[],"screenshots":[],"duration":13,"result":"SUCCESS"},{"number":18,"description":"Bob ensures that displayed items does equal [ 'Walk the dog' ]","startTime":1684893213724,"children":[],"reportData":[],"screenshots":[],"duration":13,"result":"SUCCESS"}],"userStory":{"id":"multi-actor-scenarios","storyName":"Multi-actor scenarios","path":"","type":"feature"},"startTime":1684893210863,"featureTag":{"name":"Multi-actor scenarios","type":"feature","displayName":"Multi-actor scenarios"},"tags":[{"name":"Multi-actor scenarios","type":"feature","displayName":"Multi-actor scenarios"},{"name":"retried","type":"tag","displayName":"retried"},{"name":"Linux 5.15.0-1037-azure","type":"platform","platformName":"Linux","platformVersion":"5.15.0-1037-azure","displayName":"Linux 5.15.0-1037-azure"},{"name":"firefox 113.0","type":"browser","browserName":"firefox","browserVersion":"113.0","displayName":"firefox 113.0"}],"testSource":"Playwright","context":"linux,firefox","driver":"firefox","result":"SUCCESS","duration":2948}