{"id":"multi-actor-scenarios;todo-list-app-supports-multiple-actors-using-separate-browsers;linux-5-15-0-1022-azure;chromium-107-0-5304-18","name":"Todo List App supports multiple actors using separate browsers","title":"Todo List App supports multiple actors using separate browsers","manual":false,"testSteps":[{"number":1,"description":"Alice starts with a list containing 1 items","startTime":1667734395640,"children":[{"number":2,"description":"Alice starts with an empty todo list","startTime":1667734395650,"children":[{"number":3,"description":"Alice navigates to '/'","startTime":1667734395661,"children":[],"reportData":[],"screenshots":[],"duration":324,"result":"SUCCESS"},{"number":4,"description":"Alice ensures that website title does equal 'Serenity/JS TodoApp'","startTime":1667734395996,"children":[],"reportData":[],"screenshots":[],"duration":18,"result":"SUCCESS"}],"reportData":[],"screenshots":[],"duration":364,"result":"SUCCESS"},{"number":5,"description":"Alice records an item called 'Feed the cat'","startTime":1667734396025,"children":[{"number":6,"description":"Alice enters 'Feed the cat' into \"What needs to be done?\" input box","startTime":1667734396035,"children":[],"reportData":[],"screenshots":[],"duration":48,"result":"SUCCESS"},{"number":7,"description":"Alice presses key Enter in \"What needs to be done?\" input box","startTime":1667734396093,"children":[],"reportData":[],"screenshots":[],"duration":23,"result":"SUCCESS"},{"number":8,"description":"Alice waits up to 5s, polling every 500ms, until displayed items does contain 'Feed the cat'","startTime":1667734396127,"children":[],"reportData":[],"screenshots":[],"duration":23,"result":"SUCCESS"}],"reportData":[],"screenshots":[],"duration":125,"result":"SUCCESS"}],"reportData":[],"screenshots":[],"duration":510,"result":"SUCCESS"},{"number":9,"description":"Bob starts with a list containing 1 items","startTime":1667734396173,"children":[{"number":10,"description":"Bob starts with an empty todo list","startTime":1667734396183,"children":[{"number":11,"description":"Bob navigates to '/'","startTime":1667734396194,"children":[],"reportData":[],"screenshots":[],"duration":275,"result":"SUCCESS"},{"number":12,"description":"Bob ensures that website title does equal 'Serenity/JS TodoApp'","startTime":1667734396480,"children":[],"reportData":[],"screenshots":[],"duration":7,"result":"SUCCESS"}],"reportData":[],"screenshots":[],"duration":304,"result":"SUCCESS"},{"number":13,"description":"Bob records an item called 'Walk the dog'","startTime":1667734396497,"children":[{"number":14,"description":"Bob enters 'Walk the dog' into \"What needs to be done?\" input box","startTime":1667734396507,"children":[],"reportData":[],"screenshots":[],"duration":42,"result":"SUCCESS"},{"number":15,"description":"Bob presses key Enter in \"What needs to be done?\" input box","startTime":1667734396560,"children":[],"reportData":[],"screenshots":[],"duration":20,"result":"SUCCESS"},{"number":16,"description":"Bob waits up to 5s, polling every 500ms, until displayed items does contain 'Walk the dog'","startTime":1667734396590,"children":[],"reportData":[],"screenshots":[],"duration":11,"result":"SUCCESS"}],"reportData":[],"screenshots":[],"duration":104,"result":"SUCCESS"}],"reportData":[],"screenshots":[],"duration":428,"result":"SUCCESS"},{"number":17,"description":"Alice ensures that displayed items does equal [ 'Feed the cat' ]","startTime":1667734396618,"children":[],"reportData":[],"screenshots":[],"duration":8,"result":"SUCCESS"},{"number":18,"description":"Bob ensures that displayed items does equal [ 'Walk the dog' ]","startTime":1667734396640,"children":[],"reportData":[],"screenshots":[],"duration":8,"result":"SUCCESS"}],"userStory":{"id":"multi-actor-scenarios","storyName":"Multi-actor scenarios","path":"","type":"feature"},"startTime":1667734395395,"featureTag":{"name":"Multi-actor scenarios","type":"feature","displayName":"Multi-actor scenarios"},"tags":[{"name":"Multi-actor scenarios","type":"feature","displayName":"Multi-actor scenarios"},{"name":"retried","type":"tag","displayName":"retried"},{"name":"Linux 5.15.0-1022-azure","type":"platform","platformName":"Linux","platformVersion":"5.15.0-1022-azure","displayName":"Linux 5.15.0-1022-azure"},{"name":"chromium 107.0.5304.18","type":"browser","browserName":"chromium","browserVersion":"107.0.5304.18","displayName":"chromium 107.0.5304.18"}],"testSource":"Playwright","context":"linux,chrome","driver":"chromium","result":"SUCCESS","duration":1303}